meeseeks/__init__.py
meeseeks/iam.py
meeseeks/src/__init__.py
meeseeks/src/hash/__init__.py
meeseeks/src/hash/args_and_kwargs_hash.py
meeseeks_singleton-0.4.4.dist-info/LICENSE
meeseeks_singleton-0.4.4.dist-info/METADATA
meeseeks_singleton-0.4.4.dist-info/WHEEL
meeseeks_singleton-0.4.4.dist-info/RECORD
