Metadata-Version: 2.1
Name: meeseeks-singleton
Version: 0.4.4
Summary: A Singleton python project
Author: Ximit Gaia
Author-email: im.ximit@gamil.com
Requires-Python: >=3.8,<4.0
Classifier: Programming Language :: Python :: 3
Classifier: Programming Language :: Python :: 3.8
Classifier: Programming Language :: Python :: 3.9
Classifier: Programming Language :: Python :: 3.10
Classifier: Programming Language :: Python :: 3.11
Classifier: Programming Language :: Python :: 3.12
Project-URL: bugs, https://github.com/CenturyBoys/meeseeks-singleton/issues
Project-URL: documentation, https://github.com/CenturyBoys/meeseeks-singleton/blob/main/README.md
Project-URL: homepage, https://github.com/CenturyBoys/meeseeks-singleton
Project-URL: repository, https://github.com/CenturyBoys/meeseeks-singleton/tree/main
